ansible_inspec/__init__.py
ansible_inspec/cli.py
ansible_inspec/converter.py
ansible_inspec/ansible_adapter/__init__.py
ansible_inspec/ansible_plugins/callback/compliance_reporter.py
ansible_inspec/core/__init__.py
ansible_inspec/inspec_adapter/__init__.py
ansible_inspec/reporters/__init__.py
ansible_inspec/translators/__init__.py
ansible_inspec/translators/audit_policy.py
ansible_inspec/translators/base.py
ansible_inspec/translators/custom_resource.py
ansible_inspec/translators/file_resource.py
ansible_inspec/translators/registry_key.py
ansible_inspec/translators/security_policy.py
ansible_inspec/translators/service.py
ansible_inspec/translators/windows_feature.py
ansible_inspec-0.2.5.dist-info/licenses/LICENSE
ansible_inspec-0.2.5.dist-info/licenses/NOTICE
ansible_inspec-0.2.5.dist-info/METADATA
ansible_inspec-0.2.5.dist-info/WHEEL
ansible_inspec-0.2.5.dist-info/entry_points.txt
ansible_inspec-0.2.5.dist-info/top_level.txt
ansible_inspec-0.2.5.dist-info/RECORD
