Metadata-Version: 2.4
Name: ansible-inspec
Version: 0.2.5
Summary: Compliance testing with Ansible and InSpec integration
Author: Htunn Thu Thu
License: GPL-3.0-or-later
Project-URL: Homepage, https://github.com/Htunn/ansible-inspec
Project-URL: Documentation, https://github.com/Htunn/ansible-inspec#readme
Project-URL: Repository, https://github.com/Htunn/ansible-inspec
Project-URL: Issues, https://github.com/Htunn/ansible-inspec/issues
Project-URL: Changelog, https://github.com/Htunn/ansible-inspec/blob/main/CHANGELOG.md
Project-URL: Docker Hub, https://hub.docker.com/r/htunnthuthu/ansible-inspec
Keywords: ansible,inspec,compliance,testing,infrastructure,security,automation
Classifier: Development Status :: 3 - Alpha
Classifier: Intended Audience :: Developers
Classifier: Intended Audience :: System Administrators
Classifier: License :: OSI Approved :: GNU General Public License v3 or later (GPLv3+)
Classifier: Operating System :: POSIX :: Linux
Classifier: Operating System :: MacOS :: MacOS X
Classifier: Operating System :: Microsoft :: Windows
Classifier: Programming Language :: Python :: 3
Classifier: Programming Language :: Python :: 3.8
Classifier: Programming Language :: Python :: 3.9
Classifier: Programming Language :: Python :: 3.10
Classifier: Programming Language :: Python :: 3.11
Classifier: Programming Language :: Python :: 3.12
Classifier: Topic :: System :: Systems Administration
Classifier: Topic :: Security
Requires-Python: >=3.8
License-File: LICENSE
License-File: NOTICE
Requires-Dist: ansible-core>=2.15.0
Requires-Dist: pyyaml>=6.0
Requires-Dist: jinja2>=3.1.0
Provides-Extra: dev
Requires-Dist: pytest>=7.0; extra == "dev"
Requires-Dist: pytest-cov>=4.0; extra == "dev"
Requires-Dist: black>=23.0; extra == "dev"
Requires-Dist: flake8>=6.0; extra == "dev"
Requires-Dist: mypy>=1.0; extra == "dev"
Dynamic: license-file
